anycorn/__init__.py
anycorn/__main__.py
anycorn/app_wrappers.py
anycorn/config.py
anycorn/events.py
anycorn/lifespan.py
anycorn/logging.py
anycorn/py.typed
anycorn/run.py
anycorn/statsd.py
anycorn/task_group.py
anycorn/tcp_server.py
anycorn/typing.py
anycorn/udp_server.py
anycorn/utils.py
anycorn/worker_context.py
anycorn/middleware/__init__.py
anycorn/middleware/dispatcher.py
anycorn/middleware/http_to_https.py
anycorn/middleware/proxy_fix.py
anycorn/middleware/wsgi.py
anycorn/protocol/__init__.py
anycorn/protocol/events.py
anycorn/protocol/h11.py
anycorn/protocol/h2.py
anycorn/protocol/h3.py
anycorn/protocol/http_stream.py
anycorn/protocol/quic.py
anycorn/protocol/ws_stream.py
anycorn-0.18.2.dist-info/METADATA
anycorn-0.18.2.dist-info/WHEEL
anycorn-0.18.2.dist-info/entry_points.txt
anycorn-0.18.2.dist-info/licenses/LICENSE
anycorn-0.18.2.dist-info/RECORD
