Metadata-Version: 2.4
Name: anycorn
Version: 0.18.2
Summary: A fork of Hypercorn that uses AnyIO
Author-email: Philip Graham Jones <philip.graham.jones@googlemail.com>, David Brochart <david.brochart@gmail.com>
License-Expression: MIT
License-File: LICENSE
Classifier: Development Status :: 4 - Beta
Classifier: Environment :: Web Environment
Classifier: Intended Audience :: Developers
Classifier: License :: OSI Approved :: MIT License
Classifier: Operating System :: OS Independent
Classifier: Programming Language :: Python
Classifier: Programming Language :: Python :: 3
Classifier: Programming Language :: Python :: 3.9
Classifier: Programming Language :: Python :: 3.10
Classifier: Programming Language :: Python :: 3.11
Classifier: Programming Language :: Python :: 3.12
Classifier: Programming Language :: Python :: 3.13
Classifier: Programming Language :: Python :: 3.14
Classifier: Topic :: Internet :: WWW/HTTP :: Dynamic Content
Classifier: Topic :: Software Development :: Libraries :: Python Modules
Requires-Python: >=3.9
Requires-Dist: anyio<5.0,>=4.0
Requires-Dist: exceptiongroup<2.0,>=1.1.0; python_version < '3.11'
Requires-Dist: h11
Requires-Dist: h2>=3.1.0
Requires-Dist: hpack
Requires-Dist: priority
Requires-Dist: rich-click<2.0.0,>=1.8.3
Requires-Dist: tomli; python_version < '3.11'
Requires-Dist: typing-extensions; python_version < '3.11'
Requires-Dist: wsproto>=0.14.0
Provides-Extra: h3
Requires-Dist: aioquic<2.0.0,>=1.2.0; extra == 'h3'
Provides-Extra: test
Requires-Dist: httpx; extra == 'test'
Requires-Dist: mock; extra == 'test'
Requires-Dist: mypy; extra == 'test'
Requires-Dist: pytest; extra == 'test'
Requires-Dist: trio; extra == 'test'
